rtl/stage1/clkdiv_mcp.v
// Stage 1 exercise — generated clock + multicycle path
//
// clk_div2 is a real generated clock, toggle-FF divide-by-2 off `clk`.
// acc_out is a wide accumulator whose combinational adder is deliberately
// too slow for one clk_div2 cycle, but is allowed 2 cycles via
// set_multicycle_path (accept sends a new operand only every other cycle).

module clkdiv_mcp (
    input  wire        clk,
    input  wire        rst_n,
    input  wire [31:0] operand,
    input  wire        accept,      // new operand valid, pulses once every 2 clk_div2 cycles
    output wire [31:0] acc_out,
    output wire        clk_div2_out // exposed as a port so SDC can target a stable name
);

    // ---- generated clock: divide-by-2 toggle flop ----
    reg clk_div2 = 1'b0;   // sim-only init; real reset logic below is unchanged
    always @(posedge clk) begin
        if (!rst_n)
            clk_div2 <= 1'b0;
        else
            clk_div2 <= ~clk_div2;
    end

    assign clk_div2_out = clk_div2;

    // ---- wide accumulator on the divided clock, multicycle path ----
    reg [31:0] acc = 32'd0;   // sim-only init; real reset logic below is unchanged
    wire [31:0] sum_wide;

    // deliberately deep combinational adder tree (multi-stage ripple-ish
    // chain) to model a datapath op that genuinely needs 2 clk_div2 cycles
    assign sum_wide = (acc ^ operand) + (acc & operand) + (acc | operand) + operand;

    always @(posedge clk_div2) begin
        if (!rst_n)
            acc <= 32'd0;
        else if (accept)
            acc <= sum_wide;
    end

    assign acc_out = acc;

endmodule

rtl/stage1/clkdiv_mcp_tb.v
`timescale 1ns/1ps

module clkdiv_mcp_tb;

    reg         clk = 0;
    reg         rst_n = 0;
    reg  [31:0] operand = 0;
    reg         accept = 0;
    wire [31:0] acc_out;
    wire        clk_div2_out;

    clkdiv_mcp dut (
        .clk(clk), .rst_n(rst_n),
        .operand(operand), .accept(accept),
        .acc_out(acc_out), .clk_div2_out(clk_div2_out)
    );

    always #1 clk = ~clk; // 2ns period, 500MHz

    initial begin
        $dumpfile("clkdiv_mcp.vcd");
        $dumpvars(0, clkdiv_mcp_tb);

        rst_n = 0;
        operand = 0;
        accept = 0;
        repeat (4) @(posedge clk);
        rst_n = 1;

        // drive one accept pulse every 2 clk_div2 edges (4 clk edges),
        // matching the multicycle budget given to the accumulator
        operand = 32'h0000_0001; accept = 1;
        repeat (4) @(posedge clk); accept = 0;
        repeat (4) @(posedge clk);

        operand = 32'h0000_0010; accept = 1;
        repeat (4) @(posedge clk); accept = 0;
        repeat (4) @(posedge clk);

        operand = 32'hDEAD_0000; accept = 1;
        repeat (4) @(posedge clk); accept = 0;
        repeat (8) @(posedge clk);

        $display("final acc_out = %h", acc_out);
        $finish;
    end

endmodule

rtl/stage1/clkdiv_mcp.vcd
$date
	Sat Aug  1 17:22:25 2026
$end
$version
	Icarus Verilog
$end
$timescale
	1ps
$end
$scope module clkdiv_mcp_tb $end
$var wire 1 ! clk_div2_out $end
$var wire 32 " acc_out [31:0] $end
$var reg 1 # accept $end
$var reg 1 $ clk $end
$var reg 32 % operand [31:0] $end
$var reg 1 & rst_n $end
$scope module dut $end
$var wire 32 ' acc_out [31:0] $end
$var wire 1 # accept $end
$var wire 1 $ clk $end
$var wire 1 ! clk_div2_out $end
$var wire 32 ( operand [31:0] $end
$var wire 1 & rst_n $end
$var wire 32 ) sum_wide [31:0] $end
$var reg 32 * acc [31:0] $end
$var reg 1 + clk_div2 $end
$upscope $end
$upscope $end
$enddefinitions $end
$comment Show the parameter values. $end
$dumpall
$end
#0
$dumpvars
0+
b0 *
b0 )
b0 (
b0 '
0&
b0 %
0$
0#
b0 "
0!
$end
#1000
1$
#2000
0$
#3000
1$
#4000
0$
#5000
1$
#6000
0$
#7000
1#
b11 )
b1 %
b1 (
1&
1$
#8000
0$
#9000
b111 )
b11 "
b11 '
b11 *
1!
1+
1$
#10000
0$
#11000
0!
0+
1$
#12000
0$
#13000
b1111 )
b111 "
b111 '
b111 *
1!
1+
1$
#14000
0$
#15000
0!
0+
0#
1$
#16000
0$
#17000
1!
1+
1$
#18000
0$
#19000
0!
0+
1$
#20000
0$
#21000
1!
1+
1$
#22000
0$
#23000
0!
0+
1#
b111110 )
b10000 %
b10000 (
1$
#24000
0$
#25000
b10001100 )
b111110 "
b111110 '
b111110 *
1!
1+
1$
#26000
0$
#27000
0!
0+
1$
#28000
0$
#29000
b101001000 )
b10001100 "
b10001100 '
b10001100 *
1!
1+
1$
#30000
0$
#31000
0!
0+
0#
1$
#32000
0$
#33000
1!
1+
1$
#34000
0$
#35000
0!
0+
1$
#36000
0$
#37000
1!
1+
1$
#38000
0$
#39000
0!
0+
1#
b10011100000001110000000100011000 )
b11011110101011010000000000000000 %
b11011110101011010000000000000000 (
1$
#40000
0$
#41000
b10011100000010110000001000110000 )
b10011100000001110000000100011000 "
b10011100000001110000000100011000 '
b10011100000001110000000100011000 *
1!
1+
1$
#42000
0$
#43000
0!
0+
1$
#44000
0$
#45000
b10011100000010110000010001100000 )
b10011100000010110000001000110000 "
b10011100000010110000001000110000 '
b10011100000010110000001000110000 *
1!
1+
1$
#46000
0$
#47000
0!
0+
0#
1$
