rtl/stage0/traffic_light.v
// Stage 0 exercise — traffic light FSM + datapath
// RED (4 cyc) -> GREEN (3 cyc) -> YELLOW (1 cyc) -> RED ...
// Moore FSM: outputs depend only on current state.

module traffic_light (
    input  wire clk,
    input  wire rst_n,     // active-low synchronous reset
    output wire red,
    output wire yellow,
    output wire green
);

    // state encoding
    localparam [1:0] S_RED    = 2'd0,
                      S_GREEN  = 2'd1,
                      S_YELLOW = 2'd2;

    // per-state cycle counts (datapath limits)
    localparam [2:0] RED_LIMIT    = 3'd4,
                      GREEN_LIMIT  = 3'd3,
                      YELLOW_LIMIT = 3'd1;

    reg [1:0] state, next_state;
    reg [2:0] count;          // datapath: cycles spent in current state
    reg       count_reset;    // control signal into datapath
    reg       red_r, green_r, yellow_r;  // retimed output regs

    // datapath: counter register
    always @(posedge clk) begin
        if (!rst_n)
            count <= 3'd0;
        else if (count_reset)
            count <= 3'd0;
        else
            count <= count + 3'd1;
    end

    // state register
    always @(posedge clk) begin
        if (!rst_n)
            state <= S_RED;
        else
            state <= next_state;
    end

    // retimed output register — decode moved ahead of the flop (off next_state,
    // not state), so red/green/yellow drive straight off a flop with zero
    // combinational gates after it. Functionally identical to the old
    // `assign red = (state == S_RED)`, since state <= next_state on the same
    // edge; only the position of the decode logic relative to the register
    // changed. This was the fix for the -0.56ns setup violation on `red`.
    always @(posedge clk) begin
        if (!rst_n) begin
            red_r    <= 1'b1;   // matches state's reset value S_RED
            green_r  <= 1'b0;
            yellow_r <= 1'b0;
        end else begin
            red_r    <= (next_state == S_RED);
            green_r  <= (next_state == S_GREEN);
            yellow_r <= (next_state == S_YELLOW);
        end
    end

    // next-state + count_reset logic (combinational)
    always @(*) begin
        next_state  = state;
        count_reset = 1'b0;
        case (state)
            S_RED: begin
                if (count == RED_LIMIT - 1'b1) begin
                    next_state  = S_GREEN;
                    count_reset = 1'b1;
                end
            end
            S_GREEN: begin
                if (count == GREEN_LIMIT - 1'b1) begin
                    next_state  = S_YELLOW;
                    count_reset = 1'b1;
                end
            end
            S_YELLOW: begin
                if (count == YELLOW_LIMIT - 1'b1) begin
                    next_state  = S_RED;
                    count_reset = 1'b1;
                end
            end
            default: next_state = S_RED;
        endcase
    end

    // output logic (Moore — depends only on state, now registered directly)
    assign red    = red_r;
    assign green  = green_r;
    assign yellow = yellow_r;

endmodule

rtl/stage0/traffic_light_tb.v
`timescale 1ns/1ps

module traffic_light_tb;

    reg clk = 0;
    reg rst_n = 0;
    wire red, yellow, green;

    traffic_light dut (
        .clk(clk),
        .rst_n(rst_n),
        .red(red),
        .yellow(yellow),
        .green(green)
    );

    always #5 clk = ~clk;   // 100 MHz

    integer i;
    initial begin
        $dumpfile("traffic_light.vcd");
        $dumpvars(0, traffic_light_tb);

        rst_n = 0;
        repeat (2) @(posedge clk);
        rst_n = 1;

        for (i = 0; i < 20; i = i + 1) begin
            @(posedge clk);
            $display("t=%0t state R=%b G=%b Y=%b", $time, red, green, yellow);
        end

        $finish;
    end

endmodule

rtl/stage0/traffic_light.vcd
$date
	Sat Aug  1 17:13:52 2026
$end
$version
	Icarus Verilog
$end
$timescale
	1ps
$end
$scope module traffic_light_tb $end
$var wire 1 ! yellow $end
$var wire 1 " red $end
$var wire 1 # green $end
$var reg 1 $ clk $end
$var reg 1 % rst_n $end
$var integer 32 & i [31:0] $end
$scope module dut $end
$var wire 1 $ clk $end
$var wire 1 # green $end
$var wire 1 " red $end
$var wire 1 % rst_n $end
$var wire 1 ! yellow $end
$var parameter 3 ' GREEN_LIMIT $end
$var parameter 3 ( RED_LIMIT $end
$var parameter 2 ) S_GREEN $end
$var parameter 2 * S_RED $end
$var parameter 2 + S_YELLOW $end
$var parameter 3 , YELLOW_LIMIT $end
$var reg 3 - count [2:0] $end
$var reg 1 . count_reset $end
$var reg 1 / green_r $end
$var reg 2 0 next_state [1:0] $end
$var reg 1 1 red_r $end
$var reg 2 2 state [1:0] $end
$var reg 1 3 yellow_r $end
$upscope $end
$upscope $end
$enddefinitions $end
$comment Show the parameter values. $end
$dumpall
b1 ,
b10 +
b0 *
b1 )
b100 (
b11 '
$end
#0
$dumpvars
x3
bx 2
x1
bx 0
x/
x.
bx -
bx &
0%
0$
x#
x"
x!
$end
#5000
0.
b0 0
b0 -
b0 2
0!
03
0#
0/
1"
11
1$
#10000
0$
#15000
b0 &
1%
1$
#20000
0$
#25000
b1 -
b1 &
1$
#30000
0$
#35000
b10 -
b10 &
1$
#40000
0$
#45000
1.
b1 0
b11 -
b11 &
1$
#50000
0$
#55000
0.
1#
1/
0"
01
b1 2
b0 -
b100 &
1$
#60000
0$
#65000
b1 -
b101 &
1$
#70000
0$
#75000
1.
b10 0
b10 -
b110 &
1$
#80000
0$
#85000
b0 0
1.
b0 -
b10 2
1!
13
0#
0/
b111 &
1$
#90000
0$
#95000
0.
0!
03
1"
11
b0 2
b1000 &
1$
#100000
0$
#105000
b1 -
b1001 &
1$
#110000
0$
#115000
b10 -
b1010 &
1$
#120000
0$
#125000
1.
b1 0
b11 -
b1011 &
1$
#130000
0$
#135000
0.
1#
1/
0"
01
b1 2
b0 -
b1100 &
1$
#140000
0$
#145000
b1 -
b1101 &
1$
#150000
0$
#155000
1.
b10 0
b10 -
b1110 &
1$
#160000
0$
#165000
b0 0
1.
b0 -
b10 2
1!
13
0#
0/
b1111 &
1$
#170000
0$
#175000
0.
0!
03
1"
11
b0 2
b10000 &
1$
#180000
0$
#185000
b1 -
b10001 &
1$
#190000
0$
#195000
b10 -
b10010 &
1$
#200000
0$
#205000
1.
b1 0
b11 -
b10011 &
1$
#210000
0$
#215000
0.
1#
1/
0"
01
b1 2
b0 -
b10100 &
1$
